llx/__init__.py
llx/cli.py
llx/crawler.py
llx/server.py
llx/utils.py
llx/commands/__init__.py
llx/commands/audio_to_prompt_command.py
llx/commands/chat_command.py
llx/commands/evals_command.py
llx/commands/files_to_prompt_command.py
llx/commands/prompt_command.py
llx/commands/server_command.py
llx/commands/url_to_prompt_command.py
llx/providers/__init__.py
llx/providers/anthropic_provider.py
llx/providers/deepseek_provider.py
llx/providers/gemini_provider.py
llx/providers/mistral_provider.py
llx/providers/ollama_provider.py
llx/providers/openai_provider.py
llx/providers/perplexity_provider.py
llx/providers/provider.py
llx/providers/xai_provider.py
tests/__init__.py
tests/test_cli.py
llm_tools_cli-0.1.0.dist-info/METADATA
llm_tools_cli-0.1.0.dist-info/WHEEL
llm_tools_cli-0.1.0.dist-info/entry_points.txt
llm_tools_cli-0.1.0.dist-info/top_level.txt
llm_tools_cli-0.1.0.dist-info/RECORD
