Metadata-Version: 2.2
Name: llm-tools-cli
Version: 0.1.0
Summary: A CLI tool to interact with various LLM APIs
Home-page: https://github.com/marcocampana/llx
Author: Marco Campana
Author-email: marco@xterm.it
Classifier: Programming Language :: Python :: 3
Classifier: License :: OSI Approved :: MIT License
Classifier: Operating System :: OS Independent
Requires-Python: >=3.8
Requires-Dist: click
Requires-Dist: python-dotenv
Requires-Dist: fastapi
Requires-Dist: uvicorn
Requires-Dist: pydantic
Requires-Dist: requests
Requires-Dist: beautifulsoup4
Requires-Dist: openai
Requires-Dist: anthropic
Requires-Dist: mistralai
Requires-Dist: google-generativeai
Requires-Dist: ollama
Dynamic: author
Dynamic: author-email
Dynamic: classifier
Dynamic: description
Dynamic: description-content-type
Dynamic: home-page
Dynamic: requires-dist
Dynamic: requires-python
Dynamic: summary
